pyintelx/__init__.py
pyintelx/pyintelx.py
pyintelx-0.2.7.data/scripts/pyintelx
pyintelx-0.2.7.dist-info/METADATA
pyintelx-0.2.7.dist-info/WHEEL
pyintelx-0.2.7.dist-info/top_level.txt
pyintelx-0.2.7.dist-info/RECORD
