Metadata-Version: 2.1
Name: pyintelx
Version: 0.2.7
Summary: This lib add support to use the Identity API from Intelx.io
Home-page: https://github.com/csirtamericas/pyintelxio
Author: Fermin Baudino, Einar Lanfranco, Federico Carrilao
License: MIT
Keywords: python, package, distribution
Classifier: License :: OSI Approved :: MIT License
Classifier: Natural Language :: English
Classifier: Operating System :: OS Independent
Classifier: Programming Language :: Python :: 3
Classifier: Topic :: Software Development :: Libraries :: Python Modules
Requires-Python: >=3.9
